django_revision/__init__.py
django_revision/apps.py
django_revision/constants.py
django_revision/exceptions.py
django_revision/model_mixins.py
django_revision/modeladmin_mixin.py
django_revision/models.py
django_revision/revision.py
django_revision/revision_field.py
django_revision/system_checks.py
django_revision/templatetags/__init__.py
django_revision/templatetags/revision_tags.py
django_revision/utils.py
django_revision/views.py
django_revision-2.1.0.dist-info/licenses/LICENSE
django_revision-2.1.0.dist-info/WHEEL
django_revision-2.1.0.dist-info/METADATA
django_revision-2.1.0.dist-info/RECORD
