Metadata-Version: 2.4
Name: django-revision
Version: 2.1.0
Summary: Track the git revision with every model instance saved
Keywords: Django,git,revision,clinicedc,edc
Author: Erik van Widenfelt
Author-email: Erik van Widenfelt <ew2789@gmail.com>
License-Expression: GPL-3.0-or-later
License-File: LICENSE
Classifier: Framework :: Django
Classifier: Framework :: Django :: 5.2
Classifier: Development Status :: 5 - Production/Stable
Classifier: Operating System :: OS Independent
Classifier: Programming Language :: Python :: 3.12
Classifier: Programming Language :: Python :: 3.13
Requires-Dist: gitpython>=3.1.45
Requires-Dist: python-dateutil>=2.9.0.post0
Requires-Python: >=3.12
Project-URL: Changelog, https://github.com/erikvw/django-revision/blob/main/CHANGES
Project-URL: Documentation, https://github.com/erikvw/django-revision/blob/README.rst
Project-URL: Homepage, https://github.com/erikvw/django-revision
Project-URL: Repository, https://github.com/erikvw/django-revision.git
